Workbook

Sheet Premissas
A1: HealthMatch — Modelo Financeiro (Pre-seed)
A2: Azul = premissa editável · Preto = fórmula · Verde = link entre abas · Valores em R$ · Pré-lançamento: tudo é premissa de mercado
A4: Premissas globais
A5: Ticket médio por plantão (GMV) | B5: 1300
A6: ARPA SaaS (mensal por conta) | B6: 4000
A7: Margem bruta (blended) | B7: 0.68
A8: Meses por ano | B8: 12
A11: Drivers por cenário
A12: Driver | B12: Cenário | C12: Ano 1 | D12: Ano 2 | E12: Ano 3
A13: Plantões/mês (média) | B13: Conservador | C13: 400 | D13: 2200 | E13: 6000
A14: Plantões/mês (média) | B14: Realista | C14: 800 | D14: 4500 | E14: 12000
A15: Plantões/mês (média) | B15: Otimista | C15: 1300 | D15: 8000 | E15: 22000
A16: Take-rate (% do GMV) | B16: Conservador | C16: 0.05 | D16: 0.05 | E16: 0.05
A17: Take-rate (% do GMV) | B17: Realista | C17: 0.07 | D17: 0.07 | E17: 0.07
A18: Take-rate (% do GMV) | B18: Otimista | C18: 0.08 | D18: 0.08 | E18: 0.08
A19: Contas SaaS (média ano) | B19: Conservador | C19: 2.5 | D19: 11.25 | E19: 35.42
A20: Contas SaaS (média ano) | B20: Realista | C20: 4.5 | D20: 22.5 | E20: 70
A21: Contas SaaS (média ano) | B21: Otimista | C21: 7.5 | D21: 39.58 | E21: 120.83
A23: Opex — cenário Realista (R$/ano)
A24: Linha | C24: Ano 1 | D24: Ano 2 | E24: Ano 3
A25: Pessoal | C25: 1100000 | D25: 2400000 | E25: 4800000
A26: Marketing & Vendas | C26: 150000 | D26: 600000 | E26: 1800000
A27: Infra & ferramentas | C27: 120000 | D27: 300000 | E27: 700000
A28: G&A / jurídico / contábil | C28: 120000 | D28: 300000 | E28: 700000
A29: Opex total | C29: =SUM(C25:C28) -> 1490000 | D29: =SUM(D25:D28) -> 3600000 | E29: =SUM(E25:E28) -> 8000000

Sheet ROI Coaph
A1: ROI Coaph — Economia Operacional (tese defensiva)
A2: Economia na operação da PRÓPRIA Coaph ao automatizar a gestão de plantões. NÃO é receita do HealthMatch — é a justificativa estratégica do investimento pela Coaph (paga-se mesmo sem escala externa).
A4: Premissas (editáveis)
A5: Custo atual/mês com prepostos e operação manual | B5: 240000
A6: Investimento total (pre-seed) | B6: 1500000
A7: Custo anual atual com prepostos | B7: =B5*12 -> 2880000
A9: Cenários de economia → payback do investimento
A10: Cenário | B10: % economia | C10: Economia/mês | D10: Economia/ano | E10: Payback (meses) | F10: ROI anual
A11: Conservador | B11: 0.25 | C11: =$B$5*B11 -> 60000 | D11: =C11*12 -> 720000 | E11: =$B$6/C11 -> 25 | F11: =D11/$B$6 -> 0.48
A12: Realista | B12: 0.5 | C12: =$B$5*B12 -> 120000 | D12: =C12*12 -> 1440000 | E12: =$B$6/C12 -> 12.5 | F12: =D12/$B$6 -> 0.96
A13: Otimista | B13: 0.75 | C13: =$B$5*B13 -> 180000 | D13: =C13*12 -> 2160000 | E13: =$B$6/C13 -> 8.3333333 | F13: =D13/$B$6 -> 1.44
A14: Teto teórico (não usar como base) | B14: 1 | C14: =$B$5*B14 -> 240000 | D14: =C14*12 -> 2880000 | E14: =$B$6/C14 -> 6.25 | F14: =D14/$B$6 -> 1.92
A16: Base de defesa do investimento: 25% (conservador) a 50% (realista). 100% é teto teórico — exigiria redesenho operacional total e NÃO deve ser premissa-base.
A17: Importante: esta economia NÃO se soma à receita do HealthMatch (abas Cenários/DRE). São lentes distintas — a economia justifica o aporte da Coaph; a receita é o upside da escala externa.

Sheet Cenários
A1: Projeção de receita — 3 cenários
A2: Receita líquida = Take-rate sobre GMV + Receita SaaS. GMV = plantões × ticket. (links em verde puxam da aba Premissas)
A4: Conservador
A5: Métrica | B5: Ano 1 | C5: Ano 2 | D5: Ano 3
A6: GMV (R$) | B6: =Premissas!C13*Premissas!$B$8*Premissas!$B$5 -> 6240000 | C6: =Premissas!D13*Premissas!$B$8*Premissas!$B$5 -> 34320000 | D6: =Premissas!E13*Premissas!$B$8*Premissas!$B$5 -> 93600000
A7: Receita de fee (take-rate) | B7: =B6*Premissas!C16 -> 312000 | C7: =C6*Premissas!D16 -> 1716000 | D7: =D6*Premissas!E16 -> 4680000
A8: Receita SaaS (assinatura) | B8: =Premissas!C19*Premissas!$B$6*Premissas!$B$8 -> 120000 | C8: =Premissas!D19*Premissas!$B$6*Premissas!$B$8 -> 540000 | D8: =Premissas!E19*Premissas!$B$6*Premissas!$B$8 -> 1700160
A9: Receita líquida total | B9: =B7+B8 -> 432000 | C9: =C7+C8 -> 2256000 | D9: =D7+D8 -> 6380160
A11: Realista
A12: Métrica | B12: Ano 1 | C12: Ano 2 | D12: Ano 3
A13: GMV (R$) | B13: =Premissas!C14*Premissas!$B$8*Premissas!$B$5 -> 12480000 | C13: =Premissas!D14*Premissas!$B$8*Premissas!$B$5 -> 70200000 | D13: =Premissas!E14*Premissas!$B$8*Premissas!$B$5 -> 187200000
A14: Receita de fee (take-rate) | B14: =B13*Premissas!C17 -> 873600 | C14: =C13*Premissas!D17 -> 4914000 | D14: =D13*Premissas!E17 -> 13104000
A15: Receita SaaS (assinatura) | B15: =Premissas!C20*Premissas!$B$6*Premissas!$B$8 -> 216000 | C15: =Premissas!D20*Premissas!$B$6*Premissas!$B$8 -> 1080000 | D15: =Premissas!E20*Premissas!$B$6*Premissas!$B$8 -> 3360000
A16: Receita líquida total | B16: =B14+B15 -> 1089600 | C16: =C14+C15 -> 5994000 | D16: =D14+D15 -> 16464000
A18: Otimista
A19: Métrica | B19: Ano 1 | C19: Ano 2 | D19: Ano 3
A20: GMV (R$) | B20: =Premissas!C15*Premissas!$B$8*Premissas!$B$5 -> 20280000 | C20: =Premissas!D15*Premissas!$B$8*Premissas!$B$5 -> 124800000 | D20: =Premissas!E15*Premissas!$B$8*Premissas!$B$5 -> 343200000
A21: Receita de fee (take-rate) | B21: =B20*Premissas!C18 -> 1622400 | C21: =C20*Premissas!D18 -> 9984000 | D21: =D20*Premissas!E18 -> 27456000
A22: Receita SaaS (assinatura) | B22: =Premissas!C21*Premissas!$B$6*Premissas!$B$8 -> 360000 | C22: =Premissas!D21*Premissas!$B$6*Premissas!$B$8 -> 1899840 | D22: =Premissas!E21*Premissas!$B$6*Premissas!$B$8 -> 5799840
A23: Receita líquida total | B23: =B21+B22 -> 1982400 | C23: =C21+C22 -> 11883840 | D23: =D21+D22 -> 33255840
A24: Resumo — Receita líquida por cenário
A25: Cenário | B25: Ano 1 | C25: Ano 2 | D25: Ano 3
A26: Conservador | B26: =B9 -> 432000 | C26: =C9 -> 2256000 | D26: =D9 -> 6380160
A27: Realista | B27: =B16 -> 1089600 | C27: =C16 -> 5994000 | D27: =D16 -> 16464000
A28: Otimista | B28: =B23 -> 1982400 | C28: =C23 -> 11883840 | D28: =D23 -> 33255840

Sheet DRE (Realista)
A1: DRE — cenário Realista
A2: Demonstração resumida. COGS via margem bruta (premissa). Opex puxado da aba Premissas.
A4: Linha (R$) | B4: Ano 1 | C4: Ano 2 | D4: Ano 3
A5: Receita líquida | B5: =Cenários!B16 -> 1089600 | C5: =Cenários!C16 -> 5994000 | D5: =Cenários!D16 -> 16464000
A6: (–) COGS | B6: =-B5*(1-Premissas!$B$7) -> -348672 | C6: =-C5*(1-Premissas!$B$7) -> -1918080 | D6: =-D5*(1-Premissas!$B$7) -> -5268480
A7: Lucro bruto | B7: =B5+B6 -> 740928 | C7: =C5+C6 -> 4075920 | D7: =D5+D6 -> 11195520
A8: Margem bruta % | B8: =B7/B5 -> 0.68 | C8: =C7/C5 -> 0.68 | D8: =D7/D5 -> 0.68
A9: (–) Pessoal | B9: =-Premissas!C25 -> -1100000 | C9: =-Premissas!D25 -> -2400000 | D9: =-Premissas!E25 -> -4800000
A10: (–) Marketing & Vendas | B10: =-Premissas!C26 -> -150000 | C10: =-Premissas!D26 -> -600000 | D10: =-Premissas!E26 -> -1800000
A11: (–) Infra & ferramentas | B11: =-Premissas!C27 -> -120000 | C11: =-Premissas!D27 -> -300000 | D11: =-Premissas!E27 -> -700000
A12: (–) G&A / jurídico | B12: =-Premissas!C28 -> -120000 | C12: =-Premissas!D28 -> -300000 | D12: =-Premissas!E28 -> -700000
A13: Opex total | B13: =SUM(B9:B12) -> -1490000 | C13: =SUM(C9:C12) -> -3600000 | D13: =SUM(D9:D12) -> -8000000
A14: EBITDA | B14: =B7+B13 -> -749072 | C14: =C7+C13 -> 475920 | D14: =D7+D13 -> 3195520
A15: Margem EBITDA % | B15: =B14/B5 -> -0.6874743 | C15: =C14/C5 -> 0.079399399 | D15: =D14/D5 -> 0.19409135

Sheet Métricas
A1: Unit economics (visão SaaS-only, conservadora)
A2: Visão SaaS-only para ser defensável. Economia blended (com take-rate) é maior, mas limitada por liquidez.
A4: Métrica | B4: Valor | C4: Unidade
A5: ARPA (mensal) | B5: =Premissas!$B$6 -> 4000 | C5: R$/mês
A6: Margem bruta SaaS | B6: 0.8 | C6: %
A7: CAC por conta institucional | B7: 15000 | C7: R$
A8: Churn anual (logo) | B8: 0.12 | C8: %
A9: Horizonte de LTV (cap) | B9: 36 | C9: meses
A11: Resultados
A12: Churn mensal | B12: =1-(1-B8)^(1/12) -> 0.010596241
A13: Contribuição mensal/conta | B13: =B5*B6 -> 3200
A14: LTV (36m, capado) | B14: =B13*B9 -> 115200
A15: LTV / CAC | B15: =B14/B7 -> 7.68
A16: Payback de CAC (meses) | B16: =B7/B13 -> 4.6875
A18: CAC de profissionais (oferta) na âncora | B18: 0 | C18: ≈ R$ 0 — base de 55k cooperados pré-existente

Sheet Uso dos Recursos
A1: Uso dos recursos — Pre-seed
A3: Captação total (R$) | B3: 1500000
A5: Destino | B5: % | C5: Valor (R$)
A6: Produto & Engenharia | B6: 0.55 | C6: =$B$3*B6 -> 825000
A7: GTM (Vendas & Marketing) | B7: 0.18 | C7: =$B$3*B7 -> 270000
A8: Infra & COGS iniciais | B8: 0.1 | C8: =$B$3*B8 -> 150000
A9: Jurídico / Compliance / LGPD | B9: 0.09 | C9: =$B$3*B9 -> 135000
A10: Reserva / contingência | B10: 0.08 | C10: =$B$3*B10 -> 120000
A11: Total | B11: =SUM(B6:B10) -> 1 | C11: =SUM(C6:C10) -> 1500000
A13: Runway-alvo (meses) | B13: 20
A14: Burn médio Ano 1 (DRE) | B14: ='DRE (Realista)'!B14 -> -749072
