Workbook

Sheet Premissas
A1: HealthMatch — Modelo Financeiro (pivô: contingência / gap-filling)
A2: Azul = premissa editável · Preto = fórmula · Verde = link. Core = cobrir o GAP (descobertas/no-shows), não gerir toda a escala.
A4: Premissas globais
A5: Plantão médico 12h (R$) | B5: 1200
A6: Ticket médio ponderado por classe (R$) | B6: 900
A7: Teto do trade / fee sobre o plantão (≤5%) | B7: 0.02
A8: SaaS de prontidão — Coaph (R$/mês) | B8: 8000
A9: Custo atual de prepostos (R$/mês) | B9: 240000
A10: % do custo de prepostos ligado a gaps/exceções | B10: 0.35
A11: % dos gaps cobertos com sobrepreço hoje | B11: 0.35
A12: Sobrepreço médio por cobertura emergencial (R$) | B12: 250
A13: % dos gaps que ficariam descobertos (penalidade) | B13: 0.06
A14: Penalidade média por plantão descoberto (R$) | B14: 1200
A15: Investimento PLENO em avaliação (R$) | B15: 1500000
A16: Investimento do PILOTO (R$) | B16: 300000
A18: Cenários do gap (a validar no piloto)
A19: Driver | B19: Conservador | C19: Realista | D19: Otimista
A20: Gaps cobertos/mês | B20: 400 | C20: 600 | D20: 1000
A21: % da parcela de gap automatizável | B21: 0.3 | C21: 0.45 | D21: 0.6
A23: Nota: sobrepreço e penalidade são as premissas de MAIOR peso e mais incertas — o piloto existe para validá-las. Ticket ponderado reflete o mix (médico R$1.200; enf/téc caem muito).

Sheet Economia Coaph
A1: Economia da Coaph (tese defensiva) — e o veredito de payback
A2: Âncora: parcela do custo de prepostos ligada a gaps/exceções. Honesto: a defensiva sozinha NÃO paga R$1,5mi rápido.
A4: Economia (R$/mês) | B4: Conservador | C4: Realista | D4: Otimista
A5: 1) Tempo de preposto no gap (parcela × autom.%) | B5: =(Premissas!$B$9*Premissas!$B$10)*Premissas!B21 -> 25200 | C5: =(Premissas!$B$9*Premissas!$B$10)*Premissas!C21 -> 37800 | D5: =(Premissas!$B$9*Premissas!$B$10)*Premissas!D21 -> 50400
A6: 2) Sobrepreço emergencial evitado (gaps×%×R$) | B6: =Premissas!B20*Premissas!$B$11*Premissas!$B$12 -> 35000 | C6: =Premissas!C20*Premissas!$B$11*Premissas!$B$12 -> 52500 | D6: =Premissas!D20*Premissas!$B$11*Premissas!$B$12 -> 87500
A7: 3) Penalidade evitada (gaps×%desc×R$) | B7: =Premissas!B20*Premissas!$B$13*Premissas!$B$14 -> 28800 | C7: =Premissas!C20*Premissas!$B$13*Premissas!$B$14 -> 43200 | D7: =Premissas!D20*Premissas!$B$13*Premissas!$B$14 -> 72000
A8: Economia BRUTA total / mês | B8: =SUM(B5:B7) -> 89000 | C8: =SUM(C5:C7) -> 133500 | D8: =SUM(D5:D7) -> 209900
A9: (–) Custo pago ao HealthMatch (SaaS+fee) | B9: =-'Receita HM (Coaph)'!B7 -> -15200 | C9: =-'Receita HM (Coaph)'!C7 -> -18800 | D9: =-'Receita HM (Coaph)'!D7 -> -26000
A10: Economia LÍQUIDA da Coaph / mês | B10: =B8+B9 -> 73800 | C10: =C8+C9 -> 114700 | D10: =D8+D9 -> 183900
A11: Economia líquida / ano | B11: =B10*12 -> 885600 | C11: =C10*12 -> 1376400 | D11: =D10*12 -> 2206800
A13: Payback (meses) sobre a economia líquida
A14: PILOTO (R$ 300k) — o ask atual | B14: =Premissas!$B$16/B10 -> 4.0650407 | C14: =Premissas!$B$16/C10 -> 2.6155187 | D14: =Premissas!$B$16/D10 -> 1.6313214
A15: Rodada plena (R$ 1,5 mi) — futura/ofensiva | B15: =Premissas!$B$15/B10 -> 20.325203 | C15: =Premissas!$B$15/C10 -> 13.077594 | D15: =Premissas!$B$15/D10 -> 8.1566069
A16: Floor honesto: só prepostos paga R$1,5mi em (meses) | B16: =Premissas!$B$15/B5 -> 59.52381 | C16: =Premissas!$B$15/C5 -> 39.68254 | D16: =Premissas!$B$15/D5 -> 29.761905
A18: Leitura: o PILOTO (R$300k) se paga em poucos meses mesmo no conservador. A economia depende sobretudo de sobrepreço+penalidade (linhas 2-3) — premissas que o piloto valida. Como CLIENTE, a Coaph é líquida-positiva todo mês.

Sheet Receita Incremental Coaph
A1: Receita incremental da Coaph — preencher vagas ociosas
A2: A Coaph tem contratos que não executa por falta de profissionais. A plataforma ajuda a preencher parte das vagas ociosas → margem que hoje fica na mesa. 🔹 feeling do fundador, sem dados — células editáveis.
A4: Premissas (editáveis)
A5: Vagas contratadas/mês | B5: 12000
A6: Vagas preenchidas hoje/mês | B6: 8000
A7: Valor médio da vaga (ponderado, R$) | B7: 900
A8: Margem administrativa da Coaph (<5%) | B8: 0.04
A9: Vagas ociosas/mês | B9: =B5-B6 -> 4000
A10: Taxa de ociosidade | B10: =B9/B5 -> 0.33333333
A11: GMV ocioso/mês ("dinheiro na mesa") | B11: =B9*B7 -> 3600000
A12: Margem total na mesa/mês (se preenchesse tudo) | B12: =B11*B8 -> 144000
A14: Cenários de captura pela plataforma
A15: Métrica | B15: Conservador | C15: Realista | D15: Otimista
A16: % das ociosas preenchidas via plataforma | B16: 0.15 | C16: 0.25 | D16: 0.4
A17: Vagas recuperadas/mês | B17: =$B$9*B16 -> 600 | C17: =$B$9*C16 -> 1000 | D17: =$B$9*D16 -> 1600
A18: GMV recuperado/mês | B18: =B17*$B$7 -> 540000 | C18: =C17*$B$7 -> 900000 | D18: =D17*$B$7 -> 1440000
A19: Receita incremental Coaph (margem) / mês | B19: =B18*$B$8 -> 21600 | C19: =C18*$B$8 -> 36000 | D19: =D18*$B$8 -> 57600
A20: Receita incremental Coaph / ano | B20: =B19*12 -> 259200 | C20: =C19*12 -> 432000 | D20: =D19*12 -> 691200
A22: Benefício total Coaph/mês (economia bruta + receita incremental) — realista | B22: ='Economia Coaph'!C8+C19 -> 169500
A24: Honesto: por ser cooperativa de margem fina (<5%), o ganho próprio em R$ é modesto, mas o GMV na mesa é grande e a sub-execução crônica ameaça a RENOVAÇÃO dos contratos — esse é o maior valor (estratégico). Soma-se ainda mais trabalho/renda aos cooperados.

Sheet Receita HM (Coaph)
A1: Receita do HealthMatch a partir da Coaph (SaaS + fee por gap)
A2: Modelo híbrido: mensalidade de prontidão (fixa) + fee por gap preenchido, capado no teto do trade (≤2%).
A4: Linha (R$/mês) | B4: Conservador | C4: Realista | D4: Otimista
A5: Fee por gap (gaps × ticket × teto) | B5: =Premissas!B20*Premissas!$B$6*Premissas!$B$7 -> 7200 | C5: =Premissas!C20*Premissas!$B$6*Premissas!$B$7 -> 10800 | D5: =Premissas!D20*Premissas!$B$6*Premissas!$B$7 -> 18000
A6: SaaS de prontidão | B6: =Premissas!$B$8 -> 8000 | C6: =Premissas!$B$8 -> 8000 | D6: =Premissas!$B$8 -> 8000
A7: Receita HM / mês | B7: =B5+B6 -> 15200 | C7: =C5+C6 -> 18800 | D7: =D5+D6 -> 26000
A8: Receita HM / ano | B8: =B7*12 -> 182400 | C8: =C7*12 -> 225600 | D8: =D7*12 -> 312000

Sheet Receita HM (escala)
A1: Receita do HealthMatch em escala (tese ofensiva — upside)
A2: Receita por cooperativa ≈ realista da aba Receita HM. Negócio de SaaS de contingência, modesto e previsível — não marketplace de take-rate gordo.
B4: Ano 1 | C4: Ano 2 | D4: Ano 3
A5: Cooperativas/clientes ativos (média) | B5: 1 | C5: 5 | D5: 15
A6: Receita/cliente/ano (realista) | B6: ='Receita HM (Coaph)'!C8 -> 225600 | C6: ='Receita HM (Coaph)'!C8 -> 225600 | D6: ='Receita HM (Coaph)'!C8 -> 225600
A7: Receita HM total/ano | B7: =B5*B6 -> 225600 | C7: =C5*C6 -> 1128000 | D7: =D5*D6 -> 3384000
A9: Premissa de ramp-up (clientes) e ticket idêntico ao realista; ajuste conforme pipeline. Receita Ano 3 modesta vs. marketplace anterior — coerente com margem fina.

Sheet Sensibilidade
A1: Sensibilidade — payback (meses) da economia BRUTA vs gaps/mês × automatizável%
A2: Mostra que mesmo combinações otimistas raramente pagam R$1,5mi em <30 meses só pela defensiva.
A4: gaps/mês ↓ | automatizável% → | B4: 0.3 | C4: 0.45 | D4: 0.6 | E4: 0.75
A5: 300 | B5: =Premissas!$B$15/((Premissas!$B$9*Premissas!$B$10)*0.3) -> 59.52381 | C5: =Premissas!$B$15/((Premissas!$B$9*Premissas!$B$10)*0.45) -> 39.68254 | D5: =Premissas!$B$15/((Premissas!$B$9*Premissas!$B$10)*0.6) -> 29.761905 | E5: =Premissas!$B$15/((Premissas!$B$9*Premissas!$B$10)*0.75) -> 23.809524
A6: 500 | B6: =Premissas!$B$15/((Premissas!$B$9*Premissas!$B$10)*0.3) -> 59.52381 | C6: =Premissas!$B$15/((Premissas!$B$9*Premissas!$B$10)*0.45) -> 39.68254 | D6: =Premissas!$B$15/((Premissas!$B$9*Premissas!$B$10)*0.6) -> 29.761905 | E6: =Premissas!$B$15/((Premissas!$B$9*Premissas!$B$10)*0.75) -> 23.809524
A7: 700 | B7: =Premissas!$B$15/((Premissas!$B$9*Premissas!$B$10)*0.3) -> 59.52381 | C7: =Premissas!$B$15/((Premissas!$B$9*Premissas!$B$10)*0.45) -> 39.68254 | D7: =Premissas!$B$15/((Premissas!$B$9*Premissas!$B$10)*0.6) -> 29.761905 | E7: =Premissas!$B$15/((Premissas!$B$9*Premissas!$B$10)*0.75) -> 23.809524
A8: 1000 | B8: =Premissas!$B$15/((Premissas!$B$9*Premissas!$B$10)*0.3) -> 59.52381 | C8: =Premissas!$B$15/((Premissas!$B$9*Premissas!$B$10)*0.45) -> 39.68254 | D8: =Premissas!$B$15/((Premissas!$B$9*Premissas!$B$10)*0.6) -> 29.761905 | E8: =Premissas!$B$15/((Premissas!$B$9*Premissas!$B$10)*0.75) -> 23.809524
A9: 1500 | B9: =Premissas!$B$15/((Premissas!$B$9*Premissas!$B$10)*0.3) -> 59.52381 | C9: =Premissas!$B$15/((Premissas!$B$9*Premissas!$B$10)*0.45) -> 39.68254 | D9: =Premissas!$B$15/((Premissas!$B$9*Premissas!$B$10)*0.6) -> 29.761905 | E9: =Premissas!$B$15/((Premissas!$B$9*Premissas!$B$10)*0.75) -> 23.809524
A11: Leitura: a parcela de prepostos é fixa (não depende do nº de gaps), por isso a defensiva tem teto de economia. Volume de gap importa para a RECEITA do HM e para o valor de cobertura, não para o payback via prepostos.
